[      
        {
            "item_id": "playing_card_hand",
            "item_name": "Hand of Cards",
            "item_price": 2000,
            "item_emoji": "<:Card_Playing_Set:1123719143036813322>",
            "item_rarity": "Epic",
            "item_type": "Collectable",
            "item_damage": 0,
            "isUsable": false,
            "inShop": false,
            "isEquippable": false,
            "item_description": "A complete hand of all the playing cards. A royal flush of luck!",
            "item_element": "None",
            "item_crit_chance": "0%",
            "item_projectile": "None",
            "recipe_id": "playing_card_hand",
            "item_recipe": [
                {
                    "ingredient_id": "playing_card_spades",
                    "ingredient_amount": 1
                },
                {
                    "ingredient_id": "playing_card_clubs",
                    "ingredient_amount": 1
                },
                {
                    "ingredient_id": "playing_card_diamonds",
                    "ingredient_amount": 1
                },
                {
                    "ingredient_id": "playing_card_hearts",
                    "ingredient_amount": 1
                }
            ],
            "isHuntable": false,
            "item_hunt_chance": 0,
            "item_effect": "luck + 10",
            "isMineable": false,
            "item_mine_chance": 0,
            "quote_id": "None",
            "item_quotes": [{
                "quote": "None"
            }],
            "item_sub_type": "None"
        },
        {
            "item_id": "ducktopus",
            "item_name": "Ducktopus",
            "item_price": 2000,
            "item_emoji": "<:rubber_ducktopus:1114319451085606932>",
            "item_rarity": "Epic",
            "item_type": "Collectable",
            "item_damage": 0,
            "isUsable": false,
            "inShop": false,
            "isEquippable": false,
            "item_description": "a duck with tentacles, best used in the bath, wink wink",
            "item_element": "None",
            "item_crit_chance": "0%",
            "item_projectile": "None",
            "recipe_id": "None",
            "item_recipe": [],
            "isHuntable": false,
            "item_hunt_chance": 0,
            "item_effect": "None",
            "isMineable": false,
            "item_mine_chance": 0,
            "quote_id": "None",
            "item_quotes": [{
                "quote": "None"
            }],
            "item_sub_type": "None"
        }        
    
    ]