[
    {
        "item_id": "clover",
        "item_name": "Lucky Clover",
        "item_price": 100000,
        "item_emoji": "<:FiveLeafClover:1077642975682773102>",
        "item_rarity": "Legendary",
        "item_type": "Misc",
        "item_damage": 0,
        "isUsable": false,
        "inShop": false,
        "isEquippable": true,
        "item_description": "A Legendary five-leaf clover. It's said to bring insane luck to whoever wears it.",
        "item_element": "None",
        "item_crit_chance": "0%",
        "item_projectile": "None",
        "recipe_id": "None",
        "item_recipe": [{}],
        "isHuntable": true,
        "item_hunt_chance": 0.005,
        "item_effect": "luck + 55",
        "isMineable": false,
        "item_mine_chance": 0,
        "quote_id": "None",
        "item_quotes": [{
            "quote": "None"
        }],
        "item_sub_type": "Bauble"
    },
    {
        "item_id": "goblin_talisman",
        "item_name": "Goblin Talisman",
        "item_price": 50,
        "item_emoji": "<:Goblin_Talisman:1078761460211130431>",
        "item_rarity": "Uncommon",
        "item_type": "Armor",
        "item_damage": 0,
        "isUsable": false,
        "inShop": false,
        "isEquippable": true,
        "item_description": "A small talisman once owned by a Goblin. It's said to bring luck to its bearer.",
        "item_element": "None",
        "item_crit_chance": "0%",
        "item_projectile": "None",
        "recipe_id": "None",
        "item_recipe": [
            {
                "ingredient_id": "goblin_ear",
                "ingredient_amount": 2
            },
            {
                "ingredient_id": "gold_chain",
                "ingredient_amount": 1
            }
        ],
        "isHuntable": true,
        "item_hunt_chance": 0.1,
        "item_effect": "luck + 5",
        "isMineable": false,
        "item_mine_chance": 0,
        "quote_id": "None",
        "item_quotes": [{
            "quote": "None"
        }],
        "item_sub_type": "Bauble"
    },    
    {
        "item_id": "amulet_dragon",
        "item_name": "Amulet of the Dragon",
        "item_price": 3000,
        "item_emoji": "<:Dragon_Amulet:1092440654572965888>",
        "item_rarity": "Legendary",
        "item_type": "Armor",
        "item_damage": 0,
        "isUsable": false,
        "inShop": false,
        "isEquippable": true,
        "item_description": "A powerful amulet that grants the wearer the power of the Dragon.",
        "item_element": "None",
        "item_crit_chance": "5",
        "item_projectile": "None",
        "recipe_id": "amulet_dragon",
        "item_recipe": [
            {
                "ingredient_id": "dragon_eye",
                "ingredient_amount": 1
            },
            {
                "ingredient_id": "gold_chain",
                "ingredient_amount": 1
            },
            {
                "ingredient_id": "arcane_crystal",
                "ingredient_amount": 3
            }
        ],

        "item_effect": "crit_chance + 45",
        "isMineable": false,
        "item_mine_chance": 0,
        "quote_id": "None",
        "item_quotes": [
            {
                "quote": "None"
            }
        ],
        "item_sub_type": "Necklace"
    },    
    {
        "item_id": "skeleton_key",
        "item_name": "Skeleton Key",
        "item_price": 50000,
        "item_emoji": "<:SkeletonKey:1077648544183361576>",
        "item_rarity": "Epic",
        "item_type": "Misc",
        "item_damage": 0,
        "isUsable": false,
        "inShop": false,
        "isEquippable": false,
        "item_description": "A key dropped from the Litch, used to open powerful locked doors and chests.",
        "item_element": "None",
        "item_crit_chance": "0%",
        "item_projectile": "None",
        "recipe_id": "None",
        "item_recipe": [{}],
        "isHuntable": true,
        "item_hunt_chance": 0.05,
        "item_effect": "None",
        "isMineable": false,
        "item_mine_chance": 0,
        "quote_id": "None",
        "item_quotes": [{
            "quote": "None"
        }],
        "item_sub_type": "None"
    },
    {
        "item_id": "void_pearl",
        "item_name": "Void Pearl",
        "item_price": 10000,
        "item_emoji": "<:voidPearl:1107115568420638771>",
        "item_rarity": "Rare",
        "item_type": "Misc",
        "item_damage": 0,
        "isUsable": false,
        "inShop": false,
        "isEquippable": true,
        "item_description": "A pearl that seems to absorb all light around it. It's said to be a fragment of the void itself.",
        "item_element": "None",
        "item_crit_chance": "0%",
        "item_projectile": "None",
        "recipe_id": "None",
        "item_recipe": [],
        "isHuntable": false,
        "item_hunt_chance": 0,
        "item_effect": "dodge_chance + 10",
        "isMineable": false,
        "item_mine_chance": 0,
        "item_sub_type": "None"
    },
    {
        "item_id": "dragon_heart",
        "item_name": "Dragon Heart",
        "item_price": 5000,
        "item_emoji": "<:dragonHeart:1107120020078743663>",
        "item_rarity": "Legendary",
        "item_type": "Misc",
        "item_damage": 0,
        "isUsable": false,
        "inShop": false,
        "isEquippable": true,
        "item_description": "The heart of a legendary dragon. It's said to possess immense power.",
        "item_element": "None",
        "item_crit_chance": "0%",
        "item_projectile": "None",
        "recipe_id": "None",
        "item_recipe": [],
        "isHuntable": false,
        "item_hunt_chance": 0,
        "item_effect": "health + 50",
        "isMineable": false,
        "item_mine_chance": 0,
        "item_sub_type": "None"
    }
    
]